{
    "en_en": {
        "data": {
            "content": "<div class=\"bg-grey bold font-large m-top20\"><span>noun</span></div>\n    \n    <div class=\"green margin25 m-top15\">[noncount] :a fast and complex type of jazz music :bop</div>",
            "id": "2278",
            "mean": [],
            "pronounce": "/\u02c8bi\u02d0\u02ccb\u0251\u02d0p/",
            "type": "noun",
            "word": "bebop"
        },
        "suggests": []
    },
    "en_vn": {
        "data": {
            "content": "<div class=\"bg-grey bold font-large m-top20\"><span>Danh t\u1eeb</span></div>\n    \n    <div class=\"\">(c\u00e1ch vi\u1ebft kh\u00e1c bop)</div>\n    \n    <div class=\"green margin25 m-top15\">nh\u1ea1c b\u1ed1p</div>",
            "id": "8641",
            "mean": [],
            "pronounce": "/'bi:b\u0252p/",
            "speak": {
                "uk": "https://stream-dict-laban.zdn.vn/uk/41ddf3d0240154385090ce992889036c/16e5eb5c5d2/B/bebop.mp3",
                "us": "https://stream-dict-laban.zdn.vn/us/383bcc4c6890a5690822278804b06ed3/16e5eb5c0d1/B/bebop.mp3"
            },
            "type": "Danh t\u1eeb",
            "word": "bebop"
        },
        "suggests": []
    }
}