{"en_vn": {"suggests": [], "data": {"word": "caricaturist", "id": "13239", "pronounce": "/'k\u00e6rik\u0259tj\u028a\u0259rist/", "type": "Danh t\u1eeb", "mean": [], "content": "\n    \n    <div class=\"bg-grey bold font-large m-top20\"><span>Danh t\u1eeb</span></div>\n    \n    <div class=\"green margin25 m-top15\">h\u1ecda s\u0129 bi\u1ebfm h\u1ecda</div>\n    \n", "speak": {"us": "https://stream-dict-laban.zdn.vn/us/7fd5312fa513903f0f0812c67c6e3e44/16e5de3d825/C/caricaturist.mp3", "uk": "https://stream-dict-laban.zdn.vn/uk/c6a51f6e238b425e77030a715f861b15/16e5de3ddea/C/caricaturist.mp3"}}}}