{"error": 0, "query": "debuts", "enViData": {"suggests": [{"id": "22965", "link": "/find?type=1&query=debutant", "word": "debutant"}], "best": {"id": "22965", "details": "\n<div id=\"find_word_22965\" class=\"world word_en\" rel=\"debut\">\n    <h2 class=\"fl\">debut <span class=\"color-black\">/'deibju:/</span>&nbsp;&nbsp;<span class=\"color-orange\">/'dibju:/</span></h2>\n    <div class=\"fl\">\n        <a class=\"sp_uk hidden\" rel=\"22965\" title=\"\" href=\"#\" style=\"margin-left: 0px !important;\">\u0110\u1ecdc gi\u1ecdng UK</a>\n        <a class=\"sp_us hidden\" rel=\"22965\" title=\"\" href=\"#\" style=\"margin-left: 10px !important;\">\u0110\u1ecdc gi\u1ecdng US</a>\n        <span id=\"sound\"></span>\n        <div class=\"clr\"></div>\n    </div>\n    <div class=\"clr\"></div>\n</div>\n<div id=\"content_selectable\" class=\"content\" style=\"padding-bottom: 10px\">\n    \n    <div class=\"bg-grey bold font-large m-top20\"><span>Danh t\u1eeb</span></div>\n    \n    <div class=\"\">(c\u00e1ch vi\u1ebft kh\u00e1c d\u00e9but)</div>\n    \n    <div class=\"green margin25 m-top15\">bu\u1ed5i ra m\u1eaft \u0111\u1ea7u ti\u00ean tr\u01b0\u1edbc c\u00f4ng ch\u00fang</div>\n    \n    <div class=\"color-light-blue margin25 m-top15\">he narked his d\u00e9but by beating the champion</div>\n    \n    <div class=\"margin25\">h\u1eafn \u0111\u00e1nh d\u1ea5u bu\u1ed5i ra m\u1eaft \u0111\u1ea7u ti\u00ean tr\u01b0\u1edbc c\u00f4ng ch\u00fang b\u1eb1ng tr\u1eadn \u0111\u1ea5u th\u1eafng nh\u00e0 v\u00f4 \u0111\u1ecbch</div>\n    \n</div>\n", "link": "/find?type=1&query=debut", "word": "debut"}}, "mUrl": "/find?type=1&query=debuts", "enEnData": {"suggests": [{"id": "7363", "link": "/find?type=3&query=debutante", "word": "debutante"}], "best": {"id": "7363", "details": "\n<div id=\"find_word_7363\" class=\"world word_en\" rel=\"debut\">\n    <h2 class=\"fl\">debut <span class=\"color-black\">/\u02c8de\u026a\u02ccbju\u02d0/</span>&nbsp;&nbsp;<span class=\"color-orange\"></span></h2>\n    <div class=\"fl\">\n        <a class=\"sp_uk hidden\" rel=\"7363\" title=\"\" href=\"#\" style=\"margin-left: 0px !important;\">\u0110\u1ecdc gi\u1ecdng UK</a>\n        <a class=\"sp_us hidden\" rel=\"7363\" title=\"\" href=\"#\" style=\"margin-left: 10px !important;\">\u0110\u1ecdc gi\u1ecdng US</a>\n        <span id=\"sound\"></span>\n        <div class=\"clr\"></div>\n    </div>\n    <div class=\"clr\"></div>\n</div>\n<div id=\"content_selectable\" class=\"content\" style=\"padding-bottom: 10px\">\n    \n    <div class=\"bg-grey bold font-large m-top20\"><span>noun</span></div>\n    \n    <div class=\"\">plural -buts</div>\n    \n    <div class=\"green margin25 m-top15\">[count] :the first time an actor, musician, athlete, etc., does something in public or for the public</div>\n    \n    <div class=\"color-light-blue margin25 m-top15\">my debut as a pianist</div>\n    \n    <div class=\"color-light-blue margin25 m-top15\">He made his singing debut at a very young age.</div>\n    \n    <div class=\"color-light-blue margin25 m-top15\">She is making her television/film debut. - sometimes used to refer to the first appearance of a product, sport, event, etc.</div>\n    \n    <div class=\"color-light-blue margin25 m-top15\">the debut of a new car</div>\n    \n    <div class=\"color-light-blue margin25 m-top15\">The sport's Olympic debut took place in 1980. - often used before another noun</div>\n    \n    <div class=\"color-light-blue margin25 m-top15\">her debut album/film/novel</div>\n    \n    <div class=\"bg-grey bold font-large m-top20\"><span>verb</span></div>\n    \n    <div class=\"\">debuts; debuted; debuting</div>\n    \n    <div class=\"green margin25 m-top15\">[no obj] :to appear in public for the first time :to make a debut</div>\n    \n    <div class=\"color-light-blue margin25 m-top15\">The singer debuted 10 years ago, at the age of 15.</div>\n    \n    <div class=\"color-light-blue margin25 m-top15\">The car debuted 30 years ago.</div>\n    \n    <div class=\"color-light-blue margin25 m-top15\">The computer will soon be debuting in stores across the country.</div>\n    \n    <div class=\"green margin25 m-top15\">[+ obj] :to show or provide (something, such as a product, television show, etc.) to the public for the first time</div>\n    \n    <div class=\"color-light-blue margin25 m-top15\">The network debuts a new sitcom tonight.</div>\n    \n</div>\n", "link": "/find?type=3&query=debut", "word": "debut"}}, "ftype": "1"}