{
    "en_vn": {
        "data": {
            "content": "<div class=\"bg-grey bold font-large m-top20\"><span>Ngo\u1ea1i \u0111\u1ed9ng t\u1eeb</span></div>\n    \n    <div class=\"green margin25 m-top15\">l\u1ed9t (da, v\u1ecf...) (cua, r\u1eafn...)</div>\n    \n    <div class=\"green margin25 m-top15\">(ngh\u0129a b\u00f3ng) \u0111\u1ed5i (l\u1ed1t)</div>\n    \n    <div class=\"bg-grey bold font-large m-top20\"><span>N\u1ed9i \u0111\u1ed9ng t\u1eeb</span></div>\n    \n    <div class=\"green margin25 m-top15\">l\u1ed9t da; l\u1ed9t v\u1ecf</div>\n    \n    <div class=\"green margin25 m-top15\">(ngh\u0129a b\u00f3ng) \u0111\u1ed5i l\u1ed1t</div>",
            "id": "33642",
            "mean": [],
            "pronounce": "/ig'zju:vieit/",
            "speak": {},
            "type": "Ngo\u1ea1i \u0111\u1ed9ng t\u1eeb N\u1ed9i \u0111\u1ed9ng t\u1eeb",
            "word": "exuviate"
        },
        "suggests": []
    }
}