{"error": 0, "query": "inverts", "enViData": {"suggests": [{"id": "49953", "link": "/find?type=1&query=invertase", "word": "invertase"}, {"id": "49953", "link": "/find?type=1&query=invertasre", "word": "invertasre"}, {"id": "49953", "link": "/find?type=1&query=invertebrate", "word": "invertebrate"}, {"id": "49953", "link": "/find?type=1&query=inverted", "word": "inverted"}, {"id": "49953", "link": "/find?type=1&query=inverted+commas", "word": "inverted commas"}, {"id": "49953", "link": "/find?type=1&query=inverted+snob", "word": "inverted snob"}, {"id": "49953", "link": "/find?type=1&query=inverted+snobbery", "word": "inverted snobbery"}, {"id": "49953", "link": "/find?type=1&query=inverted+sugar", "word": "inverted sugar"}, {"id": "49953", "link": "/find?type=1&query=inverter", "word": "inverter"}], "best": {"id": "49953", "details": "\n<div id=\"find_word_49953\" class=\"world word_en\" rel=\"invert\">\n    <h2 class=\"fl\">invert <span class=\"color-black\">/in'v\u025c:t/</span>&nbsp;&nbsp;<span class=\"color-orange\"></span></h2>\n    <div class=\"fl\">\n        <a class=\"sp_uk hidden\" rel=\"49953\" title=\"\" href=\"#\" style=\"margin-left: 0px !important;\">\u0110\u1ecdc gi\u1ecdng UK</a>\n        <a class=\"sp_us hidden\" rel=\"49953\" title=\"\" href=\"#\" style=\"margin-left: 10px !important;\">\u0110\u1ecdc gi\u1ecdng US</a>\n        <span id=\"sound\"></span>\n        <div class=\"clr\"></div>\n    </div>\n    <div class=\"clr\"></div>\n</div>\n<div id=\"content_selectable\" class=\"content\" style=\"padding-bottom: 10px\">\n    \n    <div class=\"bg-grey bold font-large m-top20\"><span>\u0110\u1ed9ng t\u1eeb</span></div>\n    \n    <div class=\"green margin25 m-top15\">\u0111\u1ea3o ng\u01b0\u1ee3c, l\u1ed9n ng\u01b0\u1ee3c, xoay ng\u01b0\u1ee3c</div>\n    \n    <div class=\"color-light-blue margin25 m-top15\">invert a glass</div>\n    \n    <div class=\"margin25\">\u0111\u1eb7t l\u1ed9n ng\u01b0\u1ee3c chi\u1ebfc c\u1ed1c</div>\n    \n    <div class=\"color-light-blue margin25 m-top15\">invert the word order in a sentence</div>\n    \n    <div class=\"margin25\">\u0111\u1ea3o ng\u01b0\u1ee3c th\u1ee9 t\u1ef1 t\u1eeb trong c\u00e2u</div>\n    \n</div>\n", "link": "/find?type=1&query=invert", "word": "invert"}}, "mUrl": "/find?type=1&query=inverts", "enEnData": {"suggests": [{"id": "15348", "link": "/find?type=3&query=invertebrate", "word": "invertebrate"}, {"id": "15348", "link": "/find?type=3&query=inverted+comma", "word": "inverted comma"}], "best": {"id": "15348", "details": "\n<div id=\"find_word_15348\" class=\"world word_en\" rel=\"invert\">\n    <h2 class=\"fl\">invert <span class=\"color-black\">/\u026an\u02c8v\u025at/</span>&nbsp;&nbsp;<span class=\"color-orange\"></span></h2>\n    <div class=\"fl\">\n        <a class=\"sp_uk hidden\" rel=\"15348\" title=\"\" href=\"#\" style=\"margin-left: 0px !important;\">\u0110\u1ecdc gi\u1ecdng UK</a>\n        <a class=\"sp_us hidden\" rel=\"15348\" title=\"\" href=\"#\" style=\"margin-left: 10px !important;\">\u0110\u1ecdc gi\u1ecdng US</a>\n        <span id=\"sound\"></span>\n        <div class=\"clr\"></div>\n    </div>\n    <div class=\"clr\"></div>\n</div>\n<div id=\"content_selectable\" class=\"content\" style=\"padding-bottom: 10px\">\n    \n    <div class=\"bg-grey bold font-large m-top20\"><span>verb</span></div>\n    \n    <div class=\"\">-verts; -verted; -verting</div>\n    \n    <div class=\"green margin25 m-top15\">[+ obj] formal</div>\n    \n    <div class=\"green margin25 m-top15\">to turn (something) upside down</div>\n    \n    <div class=\"color-light-blue margin25 m-top15\">invert a bowl</div>\n    \n    <div class=\"color-light-blue margin25 m-top15\">The lens inverts the image.</div>\n    \n    <div class=\"color-light-blue margin25 m-top15\">The number 9 looks like an inverted 6.</div>\n    \n    <div class=\"color-light-blue margin25 m-top15\">an inverted image</div>\n    \n    <div class=\"green margin25 m-top15\">to change the position, order, or relationship of things so that they are the opposite of what they had been</div>\n    \n    <div class=\"color-light-blue margin25 m-top15\">invert the order of two words in a sentence</div>\n    \n</div>\n", "link": "/find?type=3&query=invert", "word": "invert"}}, "ftype": "1"}