{
    "en_vn": {
        "data": {
            "content": "<div class=\"bg-grey bold font-large m-top20\"><span>N\u1ed9i \u0111\u1ed9ng t\u1eeb meseems /mi'si:mz/</span></div>\n    \n    <div class=\"green margin25 m-top15\">(t\u1eeb c\u1ed5,ngh\u0129a c\u1ed5) \u0111\u1ed1i v\u1edbi t\u00f4i, h\u00ecnh nh\u01b0</div>",
            "id": "57258",
            "mean": [],
            "pronounce": "/mi'si:md/",
            "speak": {},
            "type": "N\u1ed9i \u0111\u1ed9ng t\u1eeb meseems /mi'si:mz/",
            "word": "meseems"
        },
        "suggests": []
    }
}