{"error": 0, "query": "mohair", "enViData": {"suggests": [], "best": {"id": "58398", "details": "\n<div id=\"find_word_58398\" class=\"world word_en\" rel=\"mohair\">\n    <h2 class=\"fl\">mohair <span class=\"color-black\">/'m\u0259\u028ahe\u0259[r]/</span>&nbsp;&nbsp;<span class=\"color-orange\"></span></h2>\n    <div class=\"fl\">\n        <a class=\"sp_uk hidden\" rel=\"58398\" title=\"\" href=\"#\" style=\"margin-left: 0px !important;\">\u0110\u1ecdc gi\u1ecdng UK</a>\n        <a class=\"sp_us hidden\" rel=\"58398\" title=\"\" href=\"#\" style=\"margin-left: 10px !important;\">\u0110\u1ecdc gi\u1ecdng US</a>\n        <span id=\"sound\"></span>\n        <div class=\"clr\"></div>\n    </div>\n    <div class=\"clr\"></div>\n</div>\n<div id=\"content_selectable\" class=\"content\" style=\"padding-bottom: 10px\">\n    \n    <div class=\"bg-grey bold font-large m-top20\"><span>Danh t\u1eeb</span></div>\n    \n    <div class=\"green margin25 m-top15\">v\u1ea3i l\u00f4ng d\u00ea An-go-ra</div>\n    \n</div>\n", "link": "/find?type=1&query=mohair", "word": "mohair"}}, "mUrl": "/find?type=1&query=mohair", "enEnData": {"suggests": [], "best": {"id": "18454", "details": "\n<div id=\"find_word_18454\" class=\"world word_en\" rel=\"mohair\">\n    <h2 class=\"fl\">mohair <span class=\"color-black\">/\u02c8mo\u028a\u02cche\u025a/</span>&nbsp;&nbsp;<span class=\"color-orange\"></span></h2>\n    <div class=\"fl\">\n        <a class=\"sp_uk hidden\" rel=\"18454\" title=\"\" href=\"#\" style=\"margin-left: 0px !important;\">\u0110\u1ecdc gi\u1ecdng UK</a>\n        <a class=\"sp_us hidden\" rel=\"18454\" title=\"\" href=\"#\" style=\"margin-left: 10px !important;\">\u0110\u1ecdc gi\u1ecdng US</a>\n        <span id=\"sound\"></span>\n        <div class=\"clr\"></div>\n    </div>\n    <div class=\"clr\"></div>\n</div>\n<div id=\"content_selectable\" class=\"content\" style=\"padding-bottom: 10px\">\n    \n    <div class=\"bg-grey bold font-large m-top20\"><span>noun</span></div>\n    \n    <div class=\"green margin25 m-top15\">[noncount] :an expensive fabric or wool made from the long, soft hair of a goat from Asia</div>\n    \n    <div class=\"color-light-blue margin25 m-top15\">a sweater made of mohair and silk - often used before another noun</div>\n    \n    <div class=\"color-light-blue margin25 m-top15\">She wore her mohair hat and mittens.</div>\n    \n</div>\n", "link": "/find?type=3&query=mohair", "word": "mohair"}}, "ftype": "1"}