{
    "en_en": {
        "data": {
            "content": "<div class=\"bg-grey bold font-large m-top20\"><span>abbreviation</span></div>\n    \n    <div class=\"green margin25 m-top15\">National Rifle Association</div>\n    \n    <div class=\"green margin25 m-top15\">The NRA is an organization that is active in supporting the rights of U.S. citizens to own guns.</div>",
            "id": "19633",
            "mean": [],
            "pronounce": "",
            "type": "abbreviation",
            "word": "NRA"
        },
        "suggests": []
    }
}