{"error": 0, "query": "ra", "enViData": {"suggests": [{"id": "74110", "link": "/find?type=1&query=rabban", "word": "rabban"}, {"id": "74110", "link": "/find?type=1&query=rabbet", "word": "rabbet"}, {"id": "74110", "link": "/find?type=1&query=rabbet-joint", "word": "rabbet-joint"}, {"id": "74110", "link": "/find?type=1&query=rabbet-plane", "word": "rabbet-plane"}, {"id": "74110", "link": "/find?type=1&query=rabbet-saw", "word": "rabbet-saw"}, {"id": "74110", "link": "/find?type=1&query=rabbi", "word": "rabbi"}, {"id": "74110", "link": "/find?type=1&query=rabbin", "word": "rabbin"}, {"id": "74110", "link": "/find?type=1&query=rabbinate", "word": "rabbinate"}, {"id": "74110", "link": "/find?type=1&query=rabbinic", "word": "rabbinic"}], "best": {"id": "74110", "details": "\n<div id=\"find_word_74110\" class=\"world word_en\" rel=\"RA\">\n    <h2 class=\"fl\">RA <span class=\"color-black\">/\u0251:r'ei/</span>&nbsp;&nbsp;<span class=\"color-orange\"></span></h2>\n    <div class=\"fl\">\n        <a class=\"sp_uk hidden\" rel=\"74110\" title=\"\" href=\"#\" style=\"margin-left: 0px !important;\">\u0110\u1ecdc gi\u1ecdng UK</a>\n        <a class=\"sp_us hidden\" rel=\"74110\" title=\"\" href=\"#\" style=\"margin-left: 10px !important;\">\u0110\u1ecdc gi\u1ecdng US</a>\n        <span id=\"sound\"></span>\n        <div class=\"clr\"></div>\n    </div>\n    <div class=\"clr\"></div>\n</div>\n<div id=\"content_selectable\" class=\"content\" style=\"padding-bottom: 10px\">\n    \n    <div class=\"green margin25 m-top15\">(vi\u1ebft t\u1eaft c\u1ee7a Royal Academy; Royal Academician) H\u00e0n l\u00e2m vi\u1ec7n ho\u00e0ng gia; vi\u1ec7n s\u0129 h\u00e0n l\u00e2m vi\u1ec7n ho\u00e0ng gia</div>\n    \n    <div class=\"color-light-blue margin25 m-top15\">be an RA</div>\n    \n    <div class=\"margin25\">l\u00e0 vi\u1ec7n s\u0129 h\u00e0n l\u00e2m vi\u1ec7n ho\u00e0ng gia</div>\n    \n    <div class=\"green margin25 m-top15\">(vi\u1ebft t\u1eaft Royal Artillery) ph\u00e1o binh ho\u00e0ng gia</div>\n    \n</div>\n", "link": "/find?type=1&query=RA", "word": "RA"}}, "mUrl": "/find?type=1&query=ra", "enEnData": {"suggests": [{"id": "23696", "link": "/find?type=3&query=rabbi", "word": "rabbi"}, {"id": "23697", "link": "/find?type=3&query=rabbinic", "word": "rabbinic"}, {"id": "23698", "link": "/find?type=3&query=rabbit", "word": "rabbit"}, {"id": "23699", "link": "/find?type=3&query=rabbit+punch", "word": "rabbit punch"}, {"id": "23700", "link": "/find?type=3&query=rabbit+warren", "word": "rabbit warren"}, {"id": "23701", "link": "/find?type=3&query=rabble", "word": "rabble"}, {"id": "23702", "link": "/find?type=3&query=rabble-rouser", "word": "rabble-rouser"}, {"id": "23703", "link": "/find?type=3&query=rabid", "word": "rabid"}, {"id": "23704", "link": "/find?type=3&query=rabies", "word": "rabies"}, {"id": "23705", "link": "/find?type=3&query=raccoon", "word": "raccoon"}]}, "viEnData": {"suggests": [{"id": "28448", "link": "/find?type=2&query=ra+b%C3%A0i", "word": "ra b\u00e0i"}, {"id": "28448", "link": "/find?type=2&query=ra+b%E1%BA%A3ng", "word": "ra b\u1ea3ng"}, {"id": "28448", "link": "/find?type=2&query=ra+b%E1%BB%99", "word": "ra b\u1ed9"}, {"id": "28448", "link": "/find?type=2&query=ra+chi%E1%BB%81u", "word": "ra chi\u1ec1u"}, {"id": "28448", "link": "/find?type=2&query=ra+c%C3%B4ng", "word": "ra c\u00f4ng"}, {"id": "28448", "link": "/find?type=2&query=ra+da", "word": "ra da"}, {"id": "28448", "link": "/find?type=2&query=ra+d%C3%A1ng", "word": "ra d\u00e1ng"}, {"id": "28448", "link": "/find?type=2&query=ra+%C4%91i", "word": "ra \u0111i"}, {"id": "28448", "link": "/find?type=2&query=ra+%C4%91i+an", "word": "ra \u0111i an"}], "best": {"id": "28448", "details": "\n<div id=\"find_word_28448\" class=\"world word_vn\" rel=\"ra\">\n    <h2 class=\"fl\">ra <span class=\"color-black\"></span>&nbsp;&nbsp;<span class=\"color-orange\"></span></h2>\n    <div class=\"fl\">\n        <a class=\"sp_uk hidden\" rel=\"28448\" title=\"\" href=\"#\" style=\"margin-left: 0px !important;\">\u0110\u1ecdc gi\u1ecdng UK</a>\n        <a class=\"sp_us hidden\" rel=\"28448\" title=\"\" href=\"#\" style=\"margin-left: 10px !important;\">\u0110\u1ecdc gi\u1ecdng US</a>\n        <span id=\"sound\"></span>\n        <div class=\"clr\"></div>\n    </div>\n    <div class=\"clr\"></div>\n</div>\n<div id=\"content_selectable\" class=\"content\" style=\"padding-bottom: 10px\">\n    \n    <div class=\"bg-grey bold font-large m-top20\"><span>verb</span></div>\n    \n    <div class=\"green margin25 m-top15\">to go out; to come out</div>\n    \n    <div class=\"margin25 m-top15\">ra \u0111\u1ed3ng</div>\n    \n    <div class=\"color-light-blue margin25\">to got out into the fields to go up; to leave for</div>\n    \n    <div class=\"margin25 m-top15\">t\u1eeb qu\u00ea ra t\u1ec9nh</div>\n    \n    <div class=\"color-light-blue margin25\">to leave the country for the town to set</div>\n    \n    <div class=\"margin25 m-top15\">ra ki\u1ec3u cho th\u1ee3 l\u00e0m</div>\n    \n    <div class=\"color-light-blue margin25\">to set a pattern for the workman to work on to bear; to strike</div>\n    \n    <div class=\"margin25 m-top15\">ra qu\u1ea3</div>\n    \n    <div class=\"color-light-blue margin25\">to bear fruit to become</div>\n    \n    <div class=\"margin25 m-top15\">\u0111\u1eb9p ra</div>\n    \n    <div class=\"color-light-blue margin25\">to become beautiful to find out</div>\n    \n</div>\n", "link": "/find?type=2&query=ra", "word": "ra"}}, "ftype": "1", "synData": {"suggests": [{"id": "6165", "link": "/find?type=4&query=rabble", "word": "rabble"}, {"id": "6166", "link": "/find?type=4&query=rabble-rouser", "word": "rabble-rouser"}, {"id": "6167", "link": "/find?type=4&query=rabid", "word": "rabid"}, {"id": "6168", "link": "/find?type=4&query=race", "word": "race"}, {"id": "6169", "link": "/find?type=4&query=racial", "word": "racial"}, {"id": "6170", "link": "/find?type=4&query=rack", "word": "rack"}, {"id": "6171", "link": "/find?type=4&query=racket", "word": "racket"}, {"id": "6172", "link": "/find?type=4&query=racketeer", "word": "racketeer"}, {"id": "6173", "link": "/find?type=4&query=raconteur", "word": "raconteur"}, {"id": "6174", "link": "/find?type=4&query=racy", "word": "racy"}]}}