{
    "en_vn": {
        "data": {
            "content": "<div class=\"bg-grey bold font-large m-top20\"><span>Ngo\u1ea1i \u0111\u1ed9ng t\u1eeb</span></div>\n    \n    <div class=\"green margin25 m-top15\">l\u00e0m cho m\u1ea3nh d\u1ebb, l\u00e0m cho thon nh\u1ecf</div>\n    \n    <div class=\"bg-grey bold font-large m-top20\"><span>N\u1ed9i \u0111\u1ed9ng t\u1eeb</span></div>\n    \n    <div class=\"green margin25 m-top15\">tr\u1edf th\u00e0nh m\u1ea3nh d\u1ebb, tr\u1edf th\u00e0nh thon nh\u1ecf</div>",
            "id": "84032",
            "mean": [],
            "pronounce": "/'slend\u0259raiz/",
            "speak": {},
            "type": "Ngo\u1ea1i \u0111\u1ed9ng t\u1eeb N\u1ed9i \u0111\u1ed9ng t\u1eeb",
            "word": "slenderize"
        },
        "suggests": []
    }
}