{
    "en_vn": {
        "data": {
            "content": "<div class=\"dict--title\">T\u1eeb \u0111i\u1ec3n Anh - Vi\u1ec7t</div><div class=\"dict--content\"><table id=\"definition\" border=\"0\"><tr id=\"pa\"><td id=\"I_C\"><font color=\"#9e9e9e\">\u25d8</font></td><td id=\"C_C\" colspan=\"2\"><font color=\"#9e9e9e\">['krisp\u0259]</font></td></tr><tr id=\"tl\"><td id=\"I_C\"><font color=\"#1a76bf\">*</font></td><td id=\"C_C\" colspan=\"2\"><b><font color=\"#1a76bf\">danh t\u1eeb</font></b></td></tr><tr id=\"mn\"><td>\u00a0</td><td id=\"I_C\"><font color=\"#999\">\u25a0</font></td><td id=\"C_C\">s\u1eaft u\u1ed1n t\u00f3c</td></tr></table><i/></div>",
            "word": "crisper"
        }
    },
    "en_en": {
        "data": {
            "content": "<div class=\"dict--title\">Anh - Anh</div><div class=\"dict--content\"><k>crisper</k><blockquote>\u25a0 <cclass>noun a compartment at the bottom of a refrigerator for storing fruit and vegetables. </cclass></blockquote></div>",
            "word": "crisper"
        }
    },
    "synonyms": {
        "data": {
            "content": null,
            "word": "crisper"
        }
    },
    "grammar": {
        "data": {
            "content": null,
            "word": "crisper"
        }
    },
    "specialist": {
        "data": {
            "content": null,
            "word": "crisper"
        }
    },
    "sentences": [
        {
            "en": "Storing produce on the counter, in the <em>crisper</em> or in the cupboard makes a difference. Find out which foods go where with this guide.",
            "vi": "Tr\u1eef rau qu\u1ea3 tr\u00ean b\u00e0n b\u1ebfp, trong ng\u0103n \u0111\u1ef1ng rau qu\u1ea3 ho\u1eb7c trong ch\u1ea1n b\u1ebfp s\u1ebd c\u00f3 k\u1ebft qu\u1ea3 r\u1ea5t kh\u00e1c nhau. H\u00e3y t\u00ecm hi\u1ec3u xem th\u1ef1c ph\u1ea9m n\u00e0o \u0111\u1ec3 \u0111\u00e2u b\u1eb1ng t\u00e0i li\u1ec7u h\u01b0\u1edbng d\u1eabn n\u00e0y."
        },
        {
            "en": "If you're hauling big ticket items this year I'd like fingerprint resistant windows and a radio that only plays adult music; a television that doesn't broadcast any programs containing talking animals; and a refrigerator with a secret compartment behind the <em>crisper</em> where I can hide to talk on the phone.",
            "vi": "N\u1ebfu n\u0103m nay \u00f4ng t\u1ed1t b\u1ee5ng cho nhi\u1ec1u qu\u00e0 th\u00ec t\u00f4i xin \u01b0\u1edbc th\u00eam l\u00e0 c\u00f3 \u0111\u01b0\u1ee3c chi\u1ebfc c\u1eeda s\u1ed5 kh\u00f4ng b\u1ecb d\u00ednh d\u1ea5u tay v\u00e0 m\u1ed9t c\u00e1i \u0111\u00e0i ch\u1ec9 m\u1edf to\u00e0n nh\u1ea1c ng\u01b0\u1eddi l\u1edbn m\u00e0 th\u00f4i; m\u1ed9t c\u00e1i tivi kh\u00f4ng ph\u00e1t ch\u01b0\u01a1ng tr\u00ecnh th\u1ebf gi\u1edbi \u0111\u1ed9ng v\u1eadt n\u00e0o n\u1eefa; m\u1ed9t chi\u1ebfc t\u1ee7 l\u1ea1nh c\u00f3 c\u00e1i ng\u0103n b\u00ed m\u1eadt sau ng\u0103n \u0111\u1ef1ng rau \u0111\u1ec3 t\u00f4i c\u00f3 th\u1ec3 tr\u1ed1n v\u00e0o \u0111\u00f3 n\u00f3i chuy\u1ec7n \u0111i\u1ec7n tho\u1ea1i tho\u1ea3i m\u00e1i."
        },
        {
            "en": "The screen\n\nThe main upgrade is the screen, which is markedly <em>crisper</em>. Apple says it quadrupled the number of pixels on the iPad's 9.7-inch display to the point that there are now 3.1 million pixels on the screen, with a total resolution of 2048 by 1536 pixels. Color saturation on the device was increased 44% relative to the iPad 2, the company says.",
            "vi": "M\u00e0n h\u00ecnh\n\nN\u00e2ng c\u1ea5p ch\u00ednh n\u1eb1m \u1edf m\u00e0n h\u00ecnh, c\u1ee9ng h\u01a1n th\u1ea5y r\u00f5. Apple cho bi\u1ebft h\u1ecd \u0111\u00e3 t\u0103ng s\u1ed1 l\u01b0\u1ee3ng \u0111i\u1ec3m \u1ea3nh tr\u00ean chi\u1ebfc m\u00e0n h\u00ecnh r\u1ed9ng 9.7 inch l\u00ean g\u1ea5p 4 l\u1ea7n. M\u00e0n h\u00ecnh c\u00f3 3.1 tri\u1ec7u \u0111i\u1ec3m \u1ea3nh v\u1edbi \u0111\u1ed9 ph\u00e2n gi\u1ea3i l\u00e0 2048x1536. C\u0169ng theo th\u00f4ng tin t\u1eeb Apple, \u0111\u1ed9 b\u00e3o h\u00f2a m\u00e0u tr\u00ean thi\u1ebft b\u1ecb t\u0103ng 44% so v\u1edbi iPad 2."
        },
        {
            "en": "Who's to say whether these updates will lead people to want to purchase the new iPad, or to upgrade from a previous version. Nothing about the iPad was completely overhauled, but the overall user experience is <em>crisper</em> and speedier than before.",
            "vi": "Kh\u00f4ng ai c\u00f3 th\u1ec3 kh\u1eb3ng \u0111\u1ecbnh r\u1eb1ng li\u1ec7u nh\u1eefng n\u00e2ng c\u1ea5p n\u00e0y s\u1ebd khi\u1ebfn ng\u01b0\u1eddi ta mu\u1ed1n mua iPad m\u1edbi, ho\u1eb7c n\u00e2ng c\u1ea5p t\u1eeb c\u00e1c phi\u00ean b\u1ea3n tr\u01b0\u1edbc c\u0169 hay kh\u00f4ng. Ng\u01b0\u1eddi ta kh\u00f4ng t\u00e0i n\u00e0o n\u1eafm b\u1eaft \u0111\u01b0\u1ee3c t\u1ea5t t\u1ea7n t\u1eadt v\u1ec1 chi\u1ebfc iPad, nh\u01b0ng t\u1edbi b\u00e2y gi\u1edd ch\u1ec9 c\u00f3 th\u1ec3 nh\u1eadn x\u00e9t \u0111\u01b0\u1ee3c l\u00e0 m\u00e0n h\u00ecnh c\u1ee9ng h\u01a1n v\u00e0 nhanh h\u01a1n."
        },
        {
            "en": "Secret #3: Use perforated plastic bags to allow for some air circulation, while not letting produce dry out.   ONIONS should be stored away from other foods, particularly potatoes. Keep them in mesh bags in a cool, dark place and they will keep happily for months. You can also refrigerate onions, but be careful because the strong flavor might transfer to other foods. The exception to this is GREEN ONIONS, which should be stored in a plastic bag in a refrigerator <em>crisper</em> drawer.",
            "vi": "B\u00ed quy\u1ebft #3 : D\u00f9ng t\u00fai nh\u1ef1a \u0111\u00e2m th\u1ee7ng l\u1ed7 \u0111\u1ec3 tho\u00e1ng kh\u00ed m\u00e0 rau qu\u1ea3 v\u1eabn kh\u00f4ng b\u1ecb kh\u00f4. H\u00e0nh kh\u00f4ng n\u00ean c\u1ea5t chung v\u1edbi th\u1ef1c ph\u1ea9m kh\u00e1c, nh\u1ea5t l\u00e0 khoai t\u00e2y. C\u1ea5t h\u00e0nh trong t\u00fai l\u01b0\u1edbi \u1edf ch\u1ed7 m\u00e1t, t\u1ed1i th\u00ec h\u00e0nh s\u1ebd t\u01b0\u01a1i t\u1ed1t h\u00e0ng m\u1ea5y th\u00e1ng tr\u1eddi. B\u1ea1n c\u0169ng c\u00f3 th\u1ec3 b\u1ecf h\u00e0nh trong t\u1ee7 l\u1ea1nh, nh\u01b0ng c\u1ea9n th\u1eadn v\u00ec mu\u0300i h\u00e0nh c\u00f3 th\u1ec3 l\u00e2y qua c\u00e1c m\u00f3n \u0103n kh\u00e1c. Tr\u1eeb h\u00e0nh l\u00e1, n\u00ean tr\u1eef trong t\u00fai nh\u1ef1a \u0111\u1ec3 trong ng\u0103n \u0111\u1ef1ng rau qu\u1ea3 c\u1ee7a t\u1ee7 l\u1ea1nh."
        }
    ],
    "suggestions": []
}