{
    "en_vn": {
        "data": {
            "content": null,
            "word": "euphrasia",
            "pronounce": ""
        }
    },
    "en_en": {
        "data": {
            "content": "<div class=\"dict--title\">Anh - Anh</div><div class=\"dict--content\"><k>euphrasia</k><blockquote><cclass>[<cclass>ju:'fre\u026az\u026a\u0259<cclass>]</cclass></cclass></cclass></blockquote><blockquote>\u25a0 <cclass>noun eyebright or a related plant, especially as a herbal or homeopathic remedy for eye problems. [Genus <i>Euphrasia</i>.] </cclass></blockquote><blockquote/><blockquote><b><cclass>Origin</cclass></b></blockquote><blockquote>C18: via med. L. from Gk, lit. 'cheerfulness'. </blockquote></div>",
            "word": "euphrasia",
            "pronounce": ""
        }
    },
    "synonyms": {
        "data": {
            "content": null,
            "word": "euphrasia",
            "pronounce": ""
        }
    },
    "grammar": {
        "data": {
            "content": null,
            "word": "euphrasia",
            "pronounce": ""
        }
    },
    "specialist": {
        "data": {
            "content": null,
            "word": "euphrasia",
            "pronounce": ""
        }
    },
    "sentences": [],
    "suggestions": []
}