{
    "en_vn": {
        "data": {
            "content": null,
            "word": "firestop",
            "pronounce": ""
        }
    },
    "en_en": {
        "data": {
            "content": null,
            "word": "firestop",
            "pronounce": ""
        }
    },
    "synonyms": {
        "data": {
            "content": null,
            "word": "firestop",
            "pronounce": ""
        }
    },
    "grammar": {
        "data": {
            "content": null,
            "word": "firestop",
            "pronounce": ""
        }
    },
    "specialist": {
        "data": {
            "content": "<div class=\"dict--title\">T\u1eeb \u0111i\u1ec3n K\u1ef9 thu\u1eadt (EN)</div><div class=\"dict--content\"><table cellspacing=\"0\" cellpadding=\"0\" border=\"0\"><tbody><tr><td/><td><b><font color=\"#1a76bf\">L\u0129nh v\u1ef1c:</font></b><font color=\"#666699\"> x\u00e2y d\u1ef1ng</font></td></tr></tbody></table><table cellspacing=\"0\" cellpadding=\"0\" border=\"0\"><tbody><tr><td/><td><font color=\"#999\">\u25a0</font><font>\u00a0t\u01b0\u1eddng ch\u1eb7n l\u1eeda</font></td></tr></tbody></table><table cellspacing=\"0\" cellpadding=\"0\" border=\"0\"><tbody><tr><td/><td><font color=\"#3366ff\">Gi\u1ea3i th\u00edch EN:</font><font color=\"#333399\"> A barrier of incombustible material, such as brick, across an open area such as a hollow wall to stop the spread of fire. Also, DRAUGHT STOP.</font></td></tr></tbody></table><table cellspacing=\"0\" cellpadding=\"0\" border=\"0\"><tbody><tr><td/><td><font color=\"#3366ff\">Gi\u1ea3i th\u00edch VN:</font><font color=\"#005e00\"> Thanh ch\u1eafn b\u1eb1ng v\u1eadt li\u1ec7u kh\u00f4ng ch\u00e1y, ch\u1eb3ng h\u1ea1n nh\u01b0 g\u1ea1ch, xung quanh m\u1ed9t di\u1ec7n t\u00edch m\u1edf nh\u01b0 t\u01b0\u1eddng r\u1ed7ng, \u0111\u1ec3 ng\u0103n ng\u1ecdn l\u1eeda lan r\u1ed9ng.T\u01b0\u01a1ng t\u1ef1, DRAUGHT STOP.</font></td></tr></tbody></table></div>",
            "word": "firestop",
            "pronounce": ""
        }
    },
    "sentences": [],
    "suggestions": []
}