{
    "en_vn": {
        "data": {
            "content": null,
            "word": "Hydrus"
        }
    },
    "en_en": {
        "data": {
            "content": null,
            "word": "Hydrus"
        }
    },
    "synonyms": {
        "data": {
            "content": null,
            "word": "Hydrus"
        }
    },
    "grammar": {
        "data": {
            "content": null,
            "word": "Hydrus"
        }
    },
    "specialist": {
        "data": {
            "content": null,
            "word": "Hydrus"
        }
    },
    "sentences": [],
    "suggestions": []
}