{
    "en_vn": {
        "data": {
            "content": null,
            "word": "intrust",
            "pronounce": ""
        }
    },
    "en_en": {
        "data": {
            "content": "<div class=\"dict--title\">Anh - Anh</div><div class=\"dict--content\"><k>intrust</k><blockquote>\u25a0 <cclass>verb archaic spelling of <kref>entrust</kref>. </cclass></blockquote></div>",
            "word": "intrust",
            "pronounce": ""
        }
    },
    "synonyms": {
        "data": {
            "content": null,
            "word": "intrust",
            "pronounce": ""
        }
    },
    "grammar": {
        "data": {
            "content": null,
            "word": "intrust",
            "pronounce": ""
        }
    },
    "specialist": {
        "data": {
            "content": null,
            "word": "intrust",
            "pronounce": ""
        }
    },
    "sentences": [],
    "suggestions": []
}