{
    "en_vn": {
        "data": {
            "content": null,
            "word": "unhip"
        }
    },
    "en_en": {
        "data": {
            "content": "<div class=\"dict--title\">Anh - Anh</div><div class=\"dict--content\"><k>unhip</k><blockquote>\u25a0 <cclass>adjective (<cclass><b>unhipper</b>, <cclass><b>unhippest</b>) <cclass>informal unaware of current fashions or trends. </cclass></cclass></cclass></cclass></blockquote></div>",
            "word": "unhip"
        }
    },
    "synonyms": {
        "data": {
            "content": null,
            "word": "unhip"
        }
    },
    "grammar": {
        "data": {
            "content": null,
            "word": "unhip"
        }
    },
    "specialist": {
        "data": {
            "content": null,
            "word": "unhip"
        }
    },
    "sentences": [],
    "suggestions": []
}